LICENSE.txt
README.md
setup.py
cf_iillpackage/__init__.py
cf_iillpackage/__main__.py
cf_iillpackage/workshops.py
cf_iillpackage.egg-info/PKG-INFO
cf_iillpackage.egg-info/SOURCES.txt
cf_iillpackage.egg-info/dependency_links.txt
cf_iillpackage.egg-info/entry_points.txt
cf_iillpackage.egg-info/requires.txt
cf_iillpackage.egg-info/top_level.txt