Metadata-Version: 2.1
Name: cf-iillpackage
Version: 0.2.0
Summary: Este paquete permite consumir el API de CódigoFacilito.
Home-page: https://github.com/IsaacIsaias/cf-iillpackage
Author: Isaac Isaías López López
Author-email: isaacllisaias@gmail.com
License: MIT
Keywords: codigofacilito
Platform: UNKNOWN
Classifier: Development Status :: 3 - Alpha
Classifier: Intended Audience :: Developers
Classifier: Topic :: Software Development :: Build Tools
Classifier: License :: OSI Approved :: MIT License
Classifier: Programming Language :: Python :: 3
License-File: LICENSE.txt
